microwave-controller-main/nivel2/magnetron/latch_SR/latch_sr.v
module latch_SR ( input wire set, input wire reset,
                  output reg Q  );

  always @* begin
    case ({set, reset})
      2'b00: Q <= Q;
      2'b01: Q <= 1'b0;
      2'b10: Q <= 1'b1;
      2'b11: Q <= 1'b0;
    endcase
  end

endmodule

microwave-controller-main/nivel2/magnetron/controller_logic/controller_logic.v
module controller_logic(  input wire startn, input wire stopn, input wire clearn, input wire door_closed, input wire timer_done,
                          output wire set, output wire reset  );

  assign reset = (~door_closed) | (~clearn) | (~stopn) | timer_done;
  assign set = (~startn) & door_closed & (~timer_done);

endmodule

microwave-controller-main/nivel2/magnetron/magnetron_nivel2.v
`include "./nivel2/magnetron/latch_SR/latch_sr.v"
`include "./nivel2/magnetron/controller_logic/controller_logic.v"

module magnetron_nivel2 (    input wire startn, input wire stopn, input wire clearn, input wire door_closed, input wire timer_done,
                            output wire mag_on  );

wire saida_set;
wire saida_reset;

controller_logic controller_logic(startn, stopn, clearn, door_closed, timer_done, saida_set, saida_reset);
latch_SR latch_SR(saida_set, saida_reset, mag_on);

endmodule

microwave-controller-main/nivel2/magnetron/testbench.v
`timescale 1ns/1ns
`include "magnetron_nivel2.v"

module magnetron_nivel2_teste;

    reg startn_TB, stopn_TB, clearn_TB, door_closed_TB, timer_done_TB;
    wire mag_on_TB;

    magnetron_nivel2 DUT(
        .startn(startn_TB),
        .stopn(stopn_TB),
        .clearn(clearn_TB),
        .door_closed(door_closed_TB),
        .timer_done(timer_done_TB),
        .mag_on(mag_on_TB)
    );

    initial begin
        $dumpfile("result.vcd");
        $dumpvars(0, magnetron_nivel2_teste);

        startn_TB = 1;
        stopn_TB = 0;
        clearn_TB = 0;
        door_closed_TB = 0;
        timer_done_TB = 0;
        #5 startn_TB = 1;
        stopn_TB = 0;
        clearn_TB = 0;
        door_closed_TB = 1;
        timer_done_TB = 0;
        #5 startn_TB = 1;
        stopn_TB = 1;
        clearn_TB = 0;
        door_closed_TB = 1;
        timer_done_TB = 0;
        #5 startn_TB = 1;
        stopn_TB = 0;
        clearn_TB = 0;
        door_closed_TB = 1;
        timer_done_TB = 0;
        #5 startn_TB = 1;
        stopn_TB = 0;
        clearn_TB = 0;
        door_closed_TB = 0;
        timer_done_TB = 0;
        #5 startn_TB = 1;
        stopn_TB = 0;
        clearn_TB = 0;
        door_closed_TB = 1;
        timer_done_TB = 1;
        #5 startn_TB = 1;
        stopn_TB = 0;
        clearn_TB = 0;
        door_closed_TB = 1;
        timer_done_TB = 0;
        #5 startn_TB = 1;
        stopn_TB = 0;
        clearn_TB = 1;
        door_closed_TB = 1;
        timer_done_TB = 1;
        #5 startn_TB = 1;
        stopn_TB = 0;
        clearn_TB = 0;
        door_closed_TB = 1;
        timer_done_TB = 0;
        #5 startn_TB = 1;
        stopn_TB = 1;
        clearn_TB = 1;
        door_closed_TB = 1;
        timer_done_TB = 1;
        #5 startn_TB = 0;
        stopn_TB = 1;
        clearn_TB = 1;
        door_closed_TB = 1;
        timer_done_TB = 1;
        #5 startn_TB = 0;
        stopn_TB = 0;
        clearn_TB = 0;
        door_closed_TB = 0;
        timer_done_TB = 0;
    end

endmodule

microwave-controller-main/nivel2/magnetron/result.vcd
$date
	Sun Sep 24 21:03:09 2023
$end
$version
	Icarus Verilog
$end
$timescale
	1ns
$end
$scope module magnetron_nivel2_teste $end
$var wire 1 ! mag_on_TB $end
$var reg 1 " clearn_TB $end
$var reg 1 # door_closed_TB $end
$var reg 1 $ startn_TB $end
$var reg 1 % stopn_TB $end
$var reg 1 & timer_done_TB $end
$scope module DUT $end
$var wire 1 " clearn $end
$var wire 1 # door_closed $end
$var wire 1 $ startn $end
$var wire 1 % stopn $end
$var wire 1 & timer_done $end
$var wire 1 ' saida_set $end
$var wire 1 ( saida_reset $end
$var wire 1 ! mag_on $end
$scope module controller_logic $end
$var wire 1 " clearn $end
$var wire 1 # door_closed $end
$var wire 1 ( reset $end
$var wire 1 ' set $end
$var wire 1 $ startn $end
$var wire 1 % stopn $end
$var wire 1 & timer_done $end
$upscope $end
$scope module latch_SR $end
$var wire 1 ( reset $end
$var wire 1 ' set $end
$var reg 1 ! Q $end
$upscope $end
$upscope $end
$upscope $end
$enddefinitions $end
$comment Show the parameter values. $end
$dumpall
$end
#0
$dumpvars
1(
0'
0&
0%
1$
0#
0"
0!
$end
#5
1#
#10
1%
#15
0%
#20
0#
#25
1&
1#
#30
0&
#35
1&
1"
#40
0&
0"
#45
1&
1"
1%
#50
0$
#55
1(
0&
0#
0"
0%
