microwave-controller-main/nivel2/entrada_clock/MUX/mux.v
module mux (  input wire sel, input wire counter, input wire Hz,
              output reg Q  );

  always@*
  if (sel == 0)
    begin
      Q = counter;
    end
  else
      Q = Hz;
endmodule

microwave-controller-main/nivel2/entrada_clock/contador_0_7/counter07.v
module counter07( input wire clock, input wire clear,
                  output reg Q  );

  reg [2:0] counter07;

  always @(posedge clock or posedge clear) begin

    if (clear)
      begin
        counter07 = 3'b000;
        Q = 0;
      end
    
    else if (counter07 == 3)
      begin
        Q = 1;
        counter07 = counter07 + 1'b1;
      end
    
    else if (counter07 < 7)
      begin
        counter07 = counter07 + 1'b1;
      end
  end

endmodule

microwave-controller-main/nivel2/entrada_clock/contador_freq100/count_50hz.v
module count_50hz ( input clk,
                    output reg clk100);
                    
  reg [5:0] a = 6'b000000;
  initial clk100 = 1'b0;
  
  always @(posedge clk)
  begin
    a = a + 1'b1;
      
    if (a >= 50)
    begin
      a = 6'b000000;
      clk100 = ~clk100;
    end
  end
endmodule

microwave-controller-main/nivel2/entrada_clock/codificador/encoder.v
module encoder (  input wire [9:0] keyboard, input wire enablen,
                  output reg [3:0] BCD
);

  always @ (keyboard)
  begin
    if (enablen == 1'b0)
    begin
      case (keyboard)
        10'b1000000000: BCD = 4'b1001;
        10'b0100000000: BCD = 4'b1000;
        10'b0010000000: BCD = 4'b0111;
        10'b0001000000: BCD = 4'b0110;
        10'b0000100000: BCD = 4'b0101;
        10'b0000010000: BCD = 4'b0100;
        10'b0000001000: BCD = 4'b0011;
        10'b0000000100: BCD = 4'b0010;
        10'b0000000010: BCD = 4'b0001;
        10'b0000000001: BCD = 4'b0000;
        default: BCD = 4'bxxxx;
      endcase
    end
  end
endmodule

microwave-controller-main/nivel2/entrada_clock/entrada_clock_nivel2.v
`include "./nivel2/entrada_clock/codificador/encoder.v"
`include "./nivel2/entrada_clock/contador_0_7/counter07.v"
`include "./nivel2/entrada_clock/contador_freq100/count_50hz.v"
`include "./nivel2/entrada_clock/MUX/mux.v"

module entrada_clock_nivel2(    input [9:0] keyboard, input enablen, input clk,
                                output [3:0] D, output loadn,   output p_1hz    );

    wire relogio100, Q;
    reg keyboard_on;
    initial keyboard_on = 0;
    always @(keyboard) begin
        if(keyboard == 10'b00000_00000)
            keyboard_on <= 0;
        else
            keyboard_on <= 1;
    end
    assign loadn = ~keyboard_on;
    encoder encoder_inst(keyboard, enablen, D);
    count_50hz count_50hz_inst(clk, relogio100);
    counter07 counter07_inst(clk, loadn, Q);
    mux mux_inst(enablen, Q, relogio100, p_1hz);

endmodule

microwave-controller-main/nivel2/entrada_clock/testbench.v
`timescale 1ns/1ps
`include "entrada_clock_nivel2.v"

module entrada_clock_nivel2_teste();

    reg [9:0] keyboard;
    reg enablen;
    reg clk;
    wire [3:0] D;
    wire loadn;
    wire p_1hz;

    entrada_clock_nivel2 DUT(
        .keyboard(keyboard),
        .enablen(enablen),
        .clk(clk),
        .D(D),
        .loadn(loadn),
        .p_1hz(p_1hz)
    );

    initial begin
        $dumpfile("result.vcd");
        $dumpvars(0, entrada_clock_nivel2_teste);

            #5 keyboard = 10'b1000000000;
            clk = 1;
            enablen = 0;
            repeat(256)
                #1 clk = ~clk;

            #5 keyboard = 10'b0100000000;
            clk = 1;
            repeat(256)
                #1 clk = ~clk;

            #5 keyboard = 10'b100000000;
            clk = 1;
            enablen = 1;
            repeat(256)
                #1 clk = ~clk;

            enablen = 0;
            repeat(256)
                #1 clk = ~clk;

    end
endmodule

microwave-controller-main/nivel2/entrada_clock/result.vcd
$date
	Sun Sep 24 20:39:44 2023
$end
$version
	Icarus Verilog
$end
$timescale
	1ps
$end
$scope module entrada_clock_nivel2_teste $end
$var wire 1 ! p_1hz $end
$var wire 1 " loadn $end
$var wire 4 # D [3:0] $end
$var reg 1 $ clk $end
$var reg 1 % enablen $end
$var reg 10 & keyboard [9:0] $end
$scope module DUT $end
$var wire 1 $ clk $end
$var wire 1 % enablen $end
$var wire 10 ' keyboard [9:0] $end
$var wire 1 " loadn $end
$var wire 1 ( relogio100 $end
$var wire 1 ! p_1hz $end
$var wire 1 ) Q $end
$var wire 4 * D [3:0] $end
$var reg 1 + keyboard_on $end
$scope module count_50hz_inst $end
$var wire 1 $ clk $end
$var reg 6 , a [5:0] $end
$var reg 1 ( clk100 $end
$upscope $end
$scope module counter07_inst $end
$var wire 1 " clear $end
$var wire 1 $ clock $end
$var reg 1 ) Q $end
$var reg 3 - counter07 [2:0] $end
$upscope $end
$scope module encoder_inst $end
$var wire 1 % enablen $end
$var wire 10 . keyboard [9:0] $end
$var reg 4 / BCD [3:0] $end
$upscope $end
$scope module mux_inst $end
$var wire 1 ( Hz $end
$var wire 1 ) counter $end
$var wire 1 % sel $end
$var reg 1 ! Q $end
$upscope $end
$upscope $end
$upscope $end
$enddefinitions $end
$comment Show the parameter values. $end
$dumpall
$end
#0
$dumpvars
bx /
bx .
b0 -
b0 ,
0+
bx *
0)
0(
bx '
bx &
x%
x$
bx #
1"
0!
$end
#5000
0"
1+
b1 ,
b1001 #
b1001 *
b1001 /
0%
1$
b1000000000 &
b1000000000 '
b1000000000 .
#6000
0$
#7000
b10 ,
b1 -
1$
#8000
0$
#9000
b11 ,
b10 -
1$
#10000
0$
#11000
b100 ,
b11 -
1$
#12000
0$
#13000
1!
b101 ,
b100 -
1)
1$
#14000
0$
#15000
b110 ,
b101 -
1$
#16000
0$
#17000
b111 ,
b110 -
1$
#18000
0$
#19000
b1000 ,
b111 -
1$
#20000
0$
#21000
b1001 ,
1$
#22000
0$
#23000
b1010 ,
1$
#24000
0$
#25000
b1011 ,
1$
#26000
0$
#27000
b1100 ,
1$
#28000
0$
#29000
b1101 ,
1$
#30000
0$
#31000
b1110 ,
1$
#32000
0$
#33000
b1111 ,
1$
#34000
0$
#35000
b10000 ,
1$
#36000
0$
#37000
b10001 ,
1$
#38000
0$
#39000
b10010 ,
1$
#40000
0$
#41000
b10011 ,
1$
#42000
0$
#43000
b10100 ,
1$
#44000
0$
#45000
b10101 ,
1$
#46000
0$
#47000
b10110 ,
1$
#48000
0$
#49000
b10111 ,
1$
#50000
0$
#51000
b11000 ,
1$
#52000
0$
#53000
b11001 ,
1$
#54000
0$
#55000
b11010 ,
1$
#56000
0$
#57000
b11011 ,
1$
#58000
0$
#59000
b11100 ,
1$
#60000
0$
#61000
b11101 ,
1$
#62000
0$
#63000
b11110 ,
1$
#64000
0$
#65000
b11111 ,
1$
#66000
0$
#67000
b100000 ,
1$
#68000
0$
#69000
b100001 ,
1$
#70000
0$
#71000
b100010 ,
1$
#72000
0$
#73000
b100011 ,
1$
#74000
0$
#75000
b100100 ,
1$
#76000
0$
#77000
b100101 ,
1$
#78000
0$
#79000
b100110 ,
1$
#80000
0$
#81000
b100111 ,
1$
#82000
0$
#83000
b101000 ,
1$
#84000
0$
#85000
b101001 ,
1$
#86000
0$
#87000
b101010 ,
1$
#88000
0$
#89000
b101011 ,
1$
#90000
0$
#91000
b101100 ,
1$
#92000
0$
#93000
b101101 ,
1$
#94000
0$
#95000
b101110 ,
1$
#96000
0$
#97000
b101111 ,
1$
#98000
0$
#99000
b110000 ,
1$
#100000
0$
#101000
b110001 ,
1$
#102000
0$
#103000
1(
b0 ,
1$
#104000
0$
#105000
b1 ,
1$
#106000
0$
#107000
b10 ,
1$
#108000
0$
#109000
b11 ,
1$
#110000
0$
#111000
b100 ,
1$
#112000
0$
#113000
b101 ,
1$
#114000
0$
#115000
b110 ,
1$
#116000
0$
#117000
b111 ,
1$
#118000
0$
#119000
b1000 ,
1$
#120000
0$
#121000
b1001 ,
1$
#122000
0$
#123000
b1010 ,
1$
#124000
0$
#125000
b1011 ,
1$
#126000
0$
#127000
b1100 ,
1$
#128000
0$
#129000
b1101 ,
1$
#130000
0$
#131000
b1110 ,
1$
#132000
0$
#133000
b1111 ,
1$
#134000
0$
#135000
b10000 ,
1$
#136000
0$
#137000
b10001 ,
1$
#138000
0$
#139000
b10010 ,
1$
#140000
0$
#141000
b10011 ,
1$
#142000
0$
#143000
b10100 ,
1$
#144000
0$
#145000
b10101 ,
1$
#146000
0$
#147000
b10110 ,
1$
#148000
0$
#149000
b10111 ,
1$
#150000
0$
#151000
b11000 ,
1$
#152000
0$
#153000
b11001 ,
1$
#154000
0$
#155000
b11010 ,
1$
#156000
0$
#157000
b11011 ,
1$
#158000
0$
#159000
b11100 ,
1$
#160000
0$
#161000
b11101 ,
1$
#162000
0$
#163000
b11110 ,
1$
#164000
0$
#165000
b11111 ,
1$
#166000
0$
#167000
b100000 ,
1$
#168000
0$
#169000
b100001 ,
1$
#170000
0$
#171000
b100010 ,
1$
#172000
0$
#173000
b100011 ,
1$
#174000
0$
#175000
b100100 ,
1$
#176000
0$
#177000
b100101 ,
1$
#178000
0$
#179000
b100110 ,
1$
#180000
0$
#181000
b100111 ,
1$
#182000
0$
#183000
b101000 ,
1$
#184000
0$
#185000
b101001 ,
1$
#186000
0$
#187000
b101010 ,
1$
#188000
0$
#189000
b101011 ,
1$
#190000
0$
#191000
b101100 ,
1$
#192000
0$
#193000
b101101 ,
1$
#194000
0$
#195000
b101110 ,
1$
#196000
0$
#197000
b101111 ,
1$
#198000
0$
#199000
b110000 ,
1$
#200000
0$
#201000
b110001 ,
1$
#202000
0$
#203000
0(
b0 ,
1$
#204000
0$
#205000
b1 ,
1$
#206000
0$
#207000
b10 ,
1$
#208000
0$
#209000
b11 ,
1$
#210000
0$
#211000
b100 ,
1$
#212000
0$
#213000
b101 ,
1$
#214000
0$
#215000
b110 ,
1$
#216000
0$
#217000
b111 ,
1$
#218000
0$
#219000
b1000 ,
1$
#220000
0$
#221000
b1001 ,
1$
#222000
0$
#223000
b1010 ,
1$
#224000
0$
#225000
b1011 ,
1$
#226000
0$
#227000
b1100 ,
1$
#228000
0$
#229000
b1101 ,
1$
#230000
0$
#231000
b1110 ,
1$
#232000
0$
#233000
b1111 ,
1$
#234000
0$
#235000
b10000 ,
1$
#236000
0$
#237000
b10001 ,
1$
#238000
0$
#239000
b10010 ,
1$
#240000
0$
#241000
b10011 ,
1$
#242000
0$
#243000
b10100 ,
1$
#244000
0$
#245000
b10101 ,
1$
#246000
0$
#247000
b10110 ,
1$
#248000
0$
#249000
b10111 ,
1$
#250000
0$
#251000
b11000 ,
1$
#252000
0$
#253000
b11001 ,
1$
#254000
0$
#255000
b11010 ,
1$
#256000
0$
#257000
b11011 ,
1$
#258000
0$
#259000
b11100 ,
1$
#260000
0$
#261000
b11101 ,
1$
#266000
b1000 #
b1000 *
b1000 /
b100000000 &
b100000000 '
b100000000 .
#267000
0$
#268000
b11110 ,
1$
#269000
0$
#270000
b11111 ,
1$
#271000
0$
#272000
b100000 ,
1$
#273000
0$
#274000
b100001 ,
1$
#275000
0$
#276000
b100010 ,
1$
#277000
0$
#278000
b100011 ,
1$
#279000
0$
#280000
b100100 ,
1$
#281000
0$
#282000
b100101 ,
1$
#283000
0$
#284000
b100110 ,
1$
#285000
0$
#286000
b100111 ,
1$
#287000
0$
#288000
b101000 ,
1$
#289000
0$
#290000
b101001 ,
1$
#291000
0$
#292000
b101010 ,
1$
#293000
0$
#294000
b101011 ,
1$
#295000
0$
#296000
b101100 ,
1$
#297000
0$
#298000
b101101 ,
1$
#299000
0$
#300000
b101110 ,
1$
#301000
0$
#302000
b101111 ,
1$
#303000
0$
#304000
b110000 ,
1$
#305000
0$
#306000
b110001 ,
1$
#307000
0$
#308000
1(
b0 ,
1$
#309000
0$
#310000
b1 ,
1$
#311000
0$
#312000
b10 ,
1$
#313000
0$
#314000
b11 ,
1$
#315000
0$
#316000
b100 ,
1$
#317000
0$
#318000
b101 ,
1$
#319000
0$
#320000
b110 ,
1$
#321000
0$
#322000
b111 ,
1$
#323000
0$
#324000
b1000 ,
1$
#325000
0$
#326000
b1001 ,
1$
#327000
0$
#328000
b1010 ,
1$
#329000
0$
#330000
b1011 ,
1$
#331000
0$
#332000
b1100 ,
1$
#333000
0$
#334000
b1101 ,
1$
#335000
0$
#336000
b1110 ,
1$
#337000
0$
#338000
b1111 ,
1$
#339000
0$
#340000
b10000 ,
1$
#341000
0$
#342000
b10001 ,
1$
#343000
0$
#344000
b10010 ,
1$
#345000
0$
#346000
b10011 ,
1$
#347000
0$
#348000
b10100 ,
1$
#349000
0$
#350000
b10101 ,
1$
#351000
0$
#352000
b10110 ,
1$
#353000
0$
#354000
b10111 ,
1$
#355000
0$
#356000
b11000 ,
1$
#357000
0$
#358000
b11001 ,
1$
#359000
0$
#360000
b11010 ,
1$
#361000
0$
#362000
b11011 ,
1$
#363000
0$
#364000
b11100 ,
1$
#365000
0$
#366000
b11101 ,
1$
#367000
0$
#368000
b11110 ,
1$
#369000
0$
#370000
b11111 ,
1$
#371000
0$
#372000
b100000 ,
1$
#373000
0$
#374000
b100001 ,
1$
#375000
0$
#376000
b100010 ,
1$
#377000
0$
#378000
b100011 ,
1$
#379000
0$
#380000
b100100 ,
1$
#381000
0$
#382000
b100101 ,
1$
#383000
0$
#384000
b100110 ,
1$
#385000
0$
#386000
b100111 ,
1$
#387000
0$
#388000
b101000 ,
1$
#389000
0$
#390000
b101001 ,
1$
#391000
0$
#392000
b101010 ,
1$
#393000
0$
#394000
b101011 ,
1$
#395000
0$
#396000
b101100 ,
1$
#397000
0$
#398000
b101101 ,
1$
#399000
0$
#400000
b101110 ,
1$
#401000
0$
#402000
b101111 ,
1$
#403000
0$
#404000
b110000 ,
1$
#405000
0$
#406000
b110001 ,
1$
#407000
0$
#408000
0(
b0 ,
1$
#409000
0$
#410000
b1 ,
1$
#411000
0$
#412000
b10 ,
1$
#413000
0$
#414000
b11 ,
1$
#415000
0$
#416000
b100 ,
1$
#417000
0$
#418000
b101 ,
1$
#419000
0$
#420000
b110 ,
1$
#421000
0$
#422000
b111 ,
1$
#423000
0$
#424000
b1000 ,
1$
#425000
0$
#426000
b1001 ,
1$
#427000
0$
#428000
b1010 ,
1$
#429000
0$
#430000
b1011 ,
1$
#431000
0$
#432000
b1100 ,
1$
#433000
0$
#434000
b1101 ,
1$
#435000
0$
#436000
b1110 ,
1$
#437000
0$
#438000
b1111 ,
1$
#439000
0$
#440000
b10000 ,
1$
#441000
0$
#442000
b10001 ,
1$
#443000
0$
#444000
b10010 ,
1$
#445000
0$
#446000
b10011 ,
1$
#447000
0$
#448000
b10100 ,
1$
#449000
0$
#450000
b10101 ,
1$
#451000
0$
#452000
b10110 ,
1$
#453000
0$
#454000
b10111 ,
1$
#455000
0$
#456000
b11000 ,
1$
#457000
0$
#458000
b11001 ,
1$
#459000
0$
#460000
b11010 ,
1$
#461000
0$
#462000
b11011 ,
1$
#463000
0$
#464000
b11100 ,
1$
#465000
0$
#466000
b11101 ,
1$
#467000
0$
#468000
b11110 ,
1$
#469000
0$
#470000
b11111 ,
1$
#471000
0$
#472000
b100000 ,
1$
#473000
0$
#474000
b100001 ,
1$
#475000
0$
#476000
b100010 ,
1$
#477000
0$
#478000
b100011 ,
1$
#479000
0$
#480000
b100100 ,
1$
#481000
0$
#482000
b100101 ,
1$
#483000
0$
#484000
b100110 ,
1$
#485000
0$
#486000
b100111 ,
1$
#487000
0$
#488000
b101000 ,
1$
#489000
0$
#490000
b101001 ,
1$
#491000
0$
#492000
b101010 ,
1$
#493000
0$
#494000
b101011 ,
1$
#495000
0$
#496000
b101100 ,
1$
#497000
0$
#498000
b101101 ,
1$
#499000
0$
#500000
b101110 ,
1$
#501000
0$
#502000
b101111 ,
1$
#503000
0$
#504000
b110000 ,
1$
#505000
0$
#506000
b110001 ,
1$
#507000
0$
#508000
1(
b0 ,
1$
#509000
0$
#510000
b1 ,
1$
#511000
0$
#512000
b10 ,
1$
#513000
0$
#514000
b11 ,
1$
#515000
0$
#516000
b100 ,
1$
#517000
0$
#518000
b101 ,
1$
#519000
0$
#520000
b110 ,
1$
#521000
0$
#522000
b111 ,
1$
#527000
1%
#528000
0$
#529000
b1000 ,
1$
#530000
0$
#531000
b1001 ,
1$
#532000
0$
#533000
b1010 ,
1$
#534000
0$
#535000
b1011 ,
1$
#536000
0$
#537000
b1100 ,
1$
#538000
0$
#539000
b1101 ,
1$
#540000
0$
#541000
b1110 ,
1$
#542000
0$
#543000
b1111 ,
1$
#544000
0$
#545000
b10000 ,
1$
#546000
0$
#547000
b10001 ,
1$
#548000
0$
#549000
b10010 ,
1$
#550000
0$
#551000
b10011 ,
1$
#552000
0$
#553000
b10100 ,
1$
#554000
0$
#555000
b10101 ,
1$
#556000
0$
#557000
b10110 ,
1$
#558000
0$
#559000
b10111 ,
1$
#560000
0$
#561000
b11000 ,
1$
#562000
0$
#563000
b11001 ,
1$
#564000
0$
#565000
b11010 ,
1$
#566000
0$
#567000
b11011 ,
1$
#568000
0$
#569000
b11100 ,
1$
#570000
0$
#571000
b11101 ,
1$
#572000
0$
#573000
b11110 ,
1$
#574000
0$
#575000
b11111 ,
1$
#576000
0$
#577000
b100000 ,
1$
#578000
0$
#579000
b100001 ,
1$
#580000
0$
#581000
b100010 ,
1$
#582000
0$
#583000
b100011 ,
1$
#584000
0$
#585000
b100100 ,
1$
#586000
0$
#587000
b100101 ,
1$
#588000
0$
#589000
b100110 ,
1$
#590000
0$
#591000
b100111 ,
1$
#592000
0$
#593000
b101000 ,
1$
#594000
0$
#595000
b101001 ,
1$
#596000
0$
#597000
b101010 ,
1$
#598000
0$
#599000
b101011 ,
1$
#600000
0$
#601000
b101100 ,
1$
#602000
0$
#603000
b101101 ,
1$
#604000
0$
#605000
b101110 ,
1$
#606000
0$
#607000
b101111 ,
1$
#608000
0$
#609000
b110000 ,
1$
#610000
0$
#611000
b110001 ,
1$
#612000
0$
#613000
0!
0(
b0 ,
1$
#614000
0$
#615000
b1 ,
1$
#616000
0$
#617000
b10 ,
1$
#618000
0$
#619000
b11 ,
1$
#620000
0$
#621000
b100 ,
1$
#622000
0$
#623000
b101 ,
1$
#624000
0$
#625000
b110 ,
1$
#626000
0$
#627000
b111 ,
1$
#628000
0$
#629000
b1000 ,
1$
#630000
0$
#631000
b1001 ,
1$
#632000
0$
#633000
b1010 ,
1$
#634000
0$
#635000
b1011 ,
1$
#636000
0$
#637000
b1100 ,
1$
#638000
0$
#639000
b1101 ,
1$
#640000
0$
#641000
b1110 ,
1$
#642000
0$
#643000
b1111 ,
1$
#644000
0$
#645000
b10000 ,
1$
#646000
0$
#647000
b10001 ,
1$
#648000
0$
#649000
b10010 ,
1$
#650000
0$
#651000
b10011 ,
1$
#652000
0$
#653000
b10100 ,
1$
#654000
0$
#655000
b10101 ,
1$
#656000
0$
#657000
b10110 ,
1$
#658000
0$
#659000
b10111 ,
1$
#660000
0$
#661000
b11000 ,
1$
#662000
0$
#663000
b11001 ,
1$
#664000
0$
#665000
b11010 ,
1$
#666000
0$
#667000
b11011 ,
1$
#668000
0$
#669000
b11100 ,
1$
#670000
0$
#671000
b11101 ,
1$
#672000
0$
#673000
b11110 ,
1$
#674000
0$
#675000
b11111 ,
1$
#676000
0$
#677000
b100000 ,
1$
#678000
0$
#679000
b100001 ,
1$
#680000
0$
#681000
b100010 ,
1$
#682000
0$
#683000
b100011 ,
1$
#684000
0$
#685000
b100100 ,
1$
#686000
0$
#687000
b100101 ,
1$
#688000
0$
#689000
b100110 ,
1$
#690000
0$
#691000
b100111 ,
1$
#692000
0$
#693000
b101000 ,
1$
#694000
0$
#695000
b101001 ,
1$
#696000
0$
#697000
b101010 ,
1$
#698000
0$
#699000
b101011 ,
1$
#700000
0$
#701000
b101100 ,
1$
#702000
0$
#703000
b101101 ,
1$
#704000
0$
#705000
b101110 ,
1$
#706000
0$
#707000
b101111 ,
1$
#708000
0$
#709000
b110000 ,
1$
#710000
0$
#711000
b110001 ,
1$
#712000
0$
#713000
1!
1(
b0 ,
1$
#714000
0$
#715000
b1 ,
1$
#716000
0$
#717000
b10 ,
1$
#718000
0$
#719000
b11 ,
1$
#720000
0$
#721000
b100 ,
1$
#722000
0$
#723000
b101 ,
1$
#724000
0$
#725000
b110 ,
1$
#726000
0$
#727000
b111 ,
1$
#728000
0$
#729000
b1000 ,
1$
#730000
0$
#731000
b1001 ,
1$
#732000
0$
#733000
b1010 ,
1$
#734000
0$
#735000
b1011 ,
1$
#736000
0$
#737000
b1100 ,
1$
#738000
0$
#739000
b1101 ,
1$
#740000
0$
#741000
b1110 ,
1$
#742000
0$
#743000
b1111 ,
1$
#744000
0$
#745000
b10000 ,
1$
#746000
0$
#747000
b10001 ,
1$
#748000
0$
#749000
b10010 ,
1$
#750000
0$
#751000
b10011 ,
1$
#752000
0$
#753000
b10100 ,
1$
#754000
0$
#755000
b10101 ,
1$
#756000
0$
#757000
b10110 ,
1$
#758000
0$
#759000
b10111 ,
1$
#760000
0$
#761000
b11000 ,
1$
#762000
0$
#763000
b11001 ,
1$
#764000
0$
#765000
b11010 ,
1$
#766000
0$
#767000
b11011 ,
1$
#768000
0$
#769000
b11100 ,
1$
#770000
0$
#771000
b11101 ,
1$
#772000
0$
#773000
b11110 ,
1$
#774000
0$
#775000
b11111 ,
1$
#776000
0$
#777000
b100000 ,
1$
#778000
0$
#779000
b100001 ,
1$
#780000
0$
#781000
b100010 ,
1$
#782000
0$
#783000
b100011 ,
0%
1$
#784000
0$
#785000
b100100 ,
1$
#786000
0$
#787000
b100101 ,
1$
#788000
0$
#789000
b100110 ,
1$
#790000
0$
#791000
b100111 ,
1$
#792000
0$
#793000
b101000 ,
1$
#794000
0$
#795000
b101001 ,
1$
#796000
0$
#797000
b101010 ,
1$
#798000
0$
#799000
b101011 ,
1$
#800000
0$
#801000
b101100 ,
1$
#802000
0$
#803000
b101101 ,
1$
#804000
0$
#805000
b101110 ,
1$
#806000
0$
#807000
b101111 ,
1$
#808000
0$
#809000
b110000 ,
1$
#810000
0$
#811000
b110001 ,
1$
#812000
0$
#813000
0(
b0 ,
1$
#814000
0$
#815000
b1 ,
1$
#816000
0$
#817000
b10 ,
1$
#818000
0$
#819000
b11 ,
1$
#820000
0$
#821000
b100 ,
1$
#822000
0$
#823000
b101 ,
1$
#824000
0$
#825000
b110 ,
1$
#826000
0$
#827000
b111 ,
1$
#828000
0$
#829000
b1000 ,
1$
#830000
0$
#831000
b1001 ,
1$
#832000
0$
#833000
b1010 ,
1$
#834000
0$
#835000
b1011 ,
1$
#836000
0$
#837000
b1100 ,
1$
#838000
0$
#839000
b1101 ,
1$
#840000
0$
#841000
b1110 ,
1$
#842000
0$
#843000
b1111 ,
1$
#844000
0$
#845000
b10000 ,
1$
#846000
0$
#847000
b10001 ,
1$
#848000
0$
#849000
b10010 ,
1$
#850000
0$
#851000
b10011 ,
1$
#852000
0$
#853000
b10100 ,
1$
#854000
0$
#855000
b10101 ,
1$
#856000
0$
#857000
b10110 ,
1$
#858000
0$
#859000
b10111 ,
1$
#860000
0$
#861000
b11000 ,
1$
#862000
0$
#863000
b11001 ,
1$
#864000
0$
#865000
b11010 ,
1$
#866000
0$
#867000
b11011 ,
1$
#868000
0$
#869000
b11100 ,
1$
#870000
0$
#871000
b11101 ,
1$
#872000
0$
#873000
b11110 ,
1$
#874000
0$
#875000
b11111 ,
1$
#876000
0$
#877000
b100000 ,
1$
#878000
0$
#879000
b100001 ,
1$
#880000
0$
#881000
b100010 ,
1$
#882000
0$
#883000
b100011 ,
1$
#884000
0$
#885000
b100100 ,
1$
#886000
0$
#887000
b100101 ,
1$
#888000
0$
#889000
b100110 ,
1$
#890000
0$
#891000
b100111 ,
1$
#892000
0$
#893000
b101000 ,
1$
#894000
0$
#895000
b101001 ,
1$
#896000
0$
#897000
b101010 ,
1$
#898000
0$
#899000
b101011 ,
1$
#900000
0$
#901000
b101100 ,
1$
#902000
0$
#903000
b101101 ,
1$
#904000
0$
#905000
b101110 ,
1$
#906000
0$
#907000
b101111 ,
1$
#908000
0$
#909000
b110000 ,
1$
#910000
0$
#911000
b110001 ,
1$
#912000
0$
#913000
1(
b0 ,
1$
#914000
0$
#915000
b1 ,
1$
#916000
0$
#917000
b10 ,
1$
#918000
0$
#919000
b11 ,
1$
#920000
0$
#921000
b100 ,
1$
#922000
0$
#923000
b101 ,
1$
#924000
0$
#925000
b110 ,
1$
#926000
0$
#927000
b111 ,
1$
#928000
0$
#929000
b1000 ,
1$
#930000
0$
#931000
b1001 ,
1$
#932000
0$
#933000
b1010 ,
1$
#934000
0$
#935000
b1011 ,
1$
#936000
0$
#937000
b1100 ,
1$
#938000
0$
#939000
b1101 ,
1$
#940000
0$
#941000
b1110 ,
1$
#942000
0$
#943000
b1111 ,
1$
#944000
0$
#945000
b10000 ,
1$
#946000
0$
#947000
b10001 ,
1$
#948000
0$
#949000
b10010 ,
1$
#950000
0$
#951000
b10011 ,
1$
#952000
0$
#953000
b10100 ,
1$
#954000
0$
#955000
b10101 ,
1$
#956000
0$
#957000
b10110 ,
1$
#958000
0$
#959000
b10111 ,
1$
#960000
0$
#961000
b11000 ,
1$
#962000
0$
#963000
b11001 ,
1$
#964000
0$
#965000
b11010 ,
1$
#966000
0$
#967000
b11011 ,
1$
#968000
0$
#969000
b11100 ,
1$
#970000
0$
#971000
b11101 ,
1$
#972000
0$
#973000
b11110 ,
1$
#974000
0$
#975000
b11111 ,
1$
#976000
0$
#977000
b100000 ,
1$
#978000
0$
#979000
b100001 ,
1$
#980000
0$
#981000
b100010 ,
1$
#982000
0$
#983000
b100011 ,
1$
#984000
0$
#985000
b100100 ,
1$
#986000
0$
#987000
b100101 ,
1$
#988000
0$
#989000
b100110 ,
1$
#990000
0$
#991000
b100111 ,
1$
#992000
0$
#993000
b101000 ,
1$
#994000
0$
#995000
b101001 ,
1$
#996000
0$
#997000
b101010 ,
1$
#998000
0$
#999000
b101011 ,
1$
#1000000
0$
#1001000
b101100 ,
1$
#1002000
0$
#1003000
b101101 ,
1$
#1004000
0$
#1005000
b101110 ,
1$
#1006000
0$
#1007000
b101111 ,
1$
#1008000
0$
#1009000
b110000 ,
1$
#1010000
0$
#1011000
b110001 ,
1$
#1012000
0$
#1013000
0(
b0 ,
1$
#1014000
0$
#1015000
b1 ,
1$
#1016000
0$
#1017000
b10 ,
1$
#1018000
0$
#1019000
b11 ,
1$
#1020000
0$
#1021000
b100 ,
1$
#1022000
0$
#1023000
b101 ,
1$
#1024000
0$
#1025000
b110 ,
1$
#1026000
0$
#1027000
b111 ,
1$
#1028000
0$
#1029000
b1000 ,
1$
#1030000
0$
#1031000
b1001 ,
1$
#1032000
0$
#1033000
b1010 ,
1$
#1034000
0$
#1035000
b1011 ,
1$
#1036000
0$
#1037000
b1100 ,
1$
#1038000
0$
#1039000
b1101 ,
1$
