microwave-controller-main/nivel2/entrada_clock/codificador/encoder.v
module encoder (  input wire [9:0] keyboard, input wire enablen,
                  output reg [3:0] BCD
);

  always @ (keyboard)
  begin
    if (enablen == 1'b0)
    begin
      case (keyboard)
        10'b1000000000: BCD = 4'b1001;
        10'b0100000000: BCD = 4'b1000;
        10'b0010000000: BCD = 4'b0111;
        10'b0001000000: BCD = 4'b0110;
        10'b0000100000: BCD = 4'b0101;
        10'b0000010000: BCD = 4'b0100;
        10'b0000001000: BCD = 4'b0011;
        10'b0000000100: BCD = 4'b0010;
        10'b0000000010: BCD = 4'b0001;
        10'b0000000001: BCD = 4'b0000;
        default: BCD = 4'bxxxx;
      endcase
    end
  end
endmodule

microwave-controller-main/nivel2/entrada_clock/codificador/testbench.v
`include "encoder.v"

module testbench_encoder();

  reg [9:0] keyboard;
  reg enablen;
  wire [3:0] BCD;

  encoder dut (
    .keyboard(keyboard),
    .enablen(enablen),
    .BCD(BCD)
  );

  initial begin
    $dumpfile("result.vcd");
    $dumpvars(0, testbench_encoder);

    
    keyboard = 10'b1000000000;
    enablen = 0;
    #5;

    keyboard = 10'b0100000000;
    enablen = 0;
    #5;

    keyboard = 10'b0010000000;
    enablen = 0;
    #5;
    
    keyboard = 10'b0001000000;
    enablen = 0;
    #5;
    
    keyboard = 10'b0000100000;
    enablen = 0;
    #5;
        
    keyboard = 10'b0000010000;
    enablen = 0;
    #5;
            
    keyboard = 10'b0000001000;
    enablen = 0;
    #5;
        
    keyboard = 10'b0000000100;
    enablen = 0;
    #5;
        
    keyboard = 10'b0000000010;
    enablen = 0;
    #5;
        
    keyboard = 10'b0000000001;
    enablen = 0;
    #5;

    $finish;
  end

endmodule

microwave-controller-main/nivel2/entrada_clock/codificador/result.vcd
$date
	Sun Sep 24 20:14:21 2023
$end
$version
	Icarus Verilog
$end
$timescale
	1s
$end
$scope module testbench_encoder $end
$var wire 4 ! BCD [3:0] $end
$var reg 1 " enablen $end
$var reg 10 # keyboard [9:0] $end
$scope module dut $end
$var wire 1 " enablen $end
$var wire 10 $ keyboard [9:0] $end
$var reg 4 % BCD [3:0] $end
$upscope $end
$upscope $end
$enddefinitions $end
$comment Show the parameter values. $end
$dumpall
$end
#0
$dumpvars
b1001 %
b1000000000 $
b1000000000 #
0"
b1001 !
$end
#5
b1000 !
b1000 %
b100000000 #
b100000000 $
#10
b111 !
b111 %
b10000000 #
b10000000 $
#15
b110 !
b110 %
b1000000 #
b1000000 $
#20
b101 !
b101 %
b100000 #
b100000 $
#25
b100 !
b100 %
b10000 #
b10000 $
#30
b11 !
b11 %
b1000 #
b1000 $
#35
b10 !
b10 %
b100 #
b100 $
#40
b1 !
b1 %
b10 #
b10 $
#45
b0 !
b0 %
b1 #
b1 $
