microwave-controller-main/nivel2/contador/contador_mod_6/count_mod6.v
module count_mod6 ( input wire [3:0] data, input wire clk, input wire load, input wire en, input wire clearn, 
                    output reg [3:0] count, output wire tc, output wire count_end );

  always @(negedge clearn) 
  begin
    count <= 4'b0000;
  end

  assign count_end = (count == 4'b0000) ? 1'b1 : 1'b0;
  assign tc = en & count_end;

  always @(posedge clk)
  begin
    if (en) 
      case (count)
        4'b0101:
        begin 
          count <= 4'b0100; 
        end
        
        4'b0001:
        begin
           count <= 4'b0000;
        end
        
        4'b0000:
        begin
           count <= 4'b0101;
        end
        
        default: count <= count - 4'b0001;
      endcase
    else begin 
      if (!load)
        count <= data;
    end
  end
endmodule

microwave-controller-main/nivel2/contador/contador_mod_6/testbench.v
`timescale 1ns/1ps
`include "count_mod6.v"

module count_mod6_test();

  	reg [2:0] data; 
  	reg clk, load, en, clearn;
  	wire [3:0] count; 
  	wire tc, count_endTB;
  	integer aux;
  	count_mod6 dut(data, clk, load, en, clearn, count, tc, count_endTB);

	initial
		begin
		
			$dumpfile("result.vcd");
			$dumpvars(0,count_mod6_test);
      
      assign load = 1;
      assign en = 0; 
      assign clearn = 1;
      assign data = 3'b101;

      #10 assign load = 0;

      #10 assign load = 1;

      #10 assign en = 1; 
    end
  
  initial
    
    begin
    	clk = 1'b0;
  	end
		
  initial
    begin
      #10 clk = ~clk;
      aux = 0;
      while(aux<32)
        begin
          #10 clk = ~clk;
          aux = aux + 1;
        end
      
    end
    
endmodule

microwave-controller-main/nivel2/contador/contador_mod_6/result.vcd
$date
	Sun Sep 24 19:26:57 2023
$end
$version
	Icarus Verilog
$end
$timescale
	1ps
$end
$scope module count_mod6_test $end
$var wire 1 ! tc $end
$var wire 1 " count_endTB $end
$var wire 4 # count [3:0] $end
$var reg 1 $ clearn $end
$var reg 1 % clk $end
$var reg 3 & data [2:0] $end
$var reg 1 ' en $end
$var reg 1 ( load $end
$var integer 32 ) aux [31:0] $end
$scope module dut $end
$var wire 1 $ clearn $end
$var wire 1 % clk $end
$var wire 4 * data [3:0] $end
$var wire 1 ' en $end
$var wire 1 ( load $end
$var wire 1 ! tc $end
$var wire 1 " count_end $end
$var reg 4 + count [3:0] $end
$upscope $end
$upscope $end
$enddefinitions $end
$comment Show the parameter values. $end
$dumpall
$end
#0
$dumpvars
bx +
b101 *
bx )
1(
0'
b101 &
0%
1$
bx #
x"
0!
$end
#10000
0"
b101 #
b101 +
b0 )
1%
0(
#20000
b1 )
0%
1(
#30000
b100 #
b100 +
b10 )
1%
1'
#40000
b11 )
0%
#50000
b11 #
b11 +
b100 )
1%
#60000
b101 )
0%
#70000
b10 #
b10 +
b110 )
1%
#80000
b111 )
0%
#90000
b1 #
b1 +
b1000 )
1%
#100000
b1001 )
0%
#110000
1!
1"
b0 #
b0 +
b1010 )
1%
#120000
b1011 )
0%
#130000
0!
0"
b101 #
b101 +
b1100 )
1%
#140000
b1101 )
0%
#150000
b100 #
b100 +
b1110 )
1%
#160000
b1111 )
0%
#170000
b11 #
b11 +
b10000 )
1%
#180000
b10001 )
0%
#190000
b10 #
b10 +
b10010 )
1%
#200000
b10011 )
0%
#210000
b1 #
b1 +
b10100 )
1%
#220000
b10101 )
0%
#230000
1!
1"
b0 #
b0 +
b10110 )
1%
#240000
b10111 )
0%
#250000
0!
0"
b101 #
b101 +
b11000 )
1%
#260000
b11001 )
0%
#270000
b100 #
b100 +
b11010 )
1%
#280000
b11011 )
0%
#290000
b11 #
b11 +
b11100 )
1%
#300000
b11101 )
0%
#310000
b10 #
b10 +
b11110 )
1%
#320000
b11111 )
0%
#330000
b1 #
b1 +
b100000 )
1%
